src/__init__.py
src/pyreg.py
src/pystata.py
pystata-0.0.1.dist-info/LICENSE
pystata-0.0.1.dist-info/METADATA
pystata-0.0.1.dist-info/WHEEL
pystata-0.0.1.dist-info/top_level.txt
pystata-0.0.1.dist-info/RECORD
