Metadata-Version: 2.1
Name: pystata
Version: 0.0.1
Summary: Access Stata within python
Author: Shin Chen
Author-email: <jiayuanchen@outlook.com>
Keywords: python,pandas,regression,Stata
Classifier: Development Status :: 1 - Planning
Classifier: Intended Audience :: Developers
Classifier: Programming Language :: Python :: 3
Classifier: Operating System :: Unix
Classifier: Operating System :: MacOS :: MacOS X
Classifier: Operating System :: Microsoft :: Windows
License-File: LICENSE
Requires-Dist: pandas
